{
  "checkpoint": "models/checkpoint_actor.pth",
  "episodes_per_mode": 3,
  "noise_std": 0.0,
  "use_training_exploration": false,
  "seed": 15026,
  "aggregate": {
    "down_to_up": {
      "steps_mean": 1000.0,
      "steps_max": 1000.0,
      "total_reward_mean": -6.011016491840053,
      "total_reward_max": -5.8699046638878105,
      "peak_target_score_mean": 7.435634414128829e-07,
      "peak_target_score_max": 7.959300750739359e-07,
      "peak_effective_target_score_mean": 7.435634414128829e-07,
      "peak_effective_target_score_max": 7.959300750739359e-07,
      "final_hold_mean": 0.0,
      "final_hold_max": 0.0,
      "overall_hold_mean": 0.0,
      "overall_hold_max": 0.0,
      "max_in_target_streak_mean": 0.0,
      "max_in_target_streak_max": 0.0,
      "near_target_fraction_mean": 0.0,
      "near_target_fraction_max": 0.0,
      "near_fast_fraction_mean": 0.0,
      "near_fast_fraction_max": 0.0,
      "mean_angular_speed_near_mean": 0.0,
      "mean_angular_speed_near_max": 0.0,
      "max_abs_cart_x_mean": 0.13406992679644578,
      "max_abs_cart_x_max": 0.13813924428940755,
      "mean_abs_action_mean": 0.004966937709134072,
      "mean_abs_action_max": 0.00613209316819848,
      "saturated_action_fraction_mean": 0.0,
      "saturated_action_fraction_max": 0.0,
      "pre_switch_final_hold_mean": 0.0,
      "pre_switch_final_hold_max": 0.0,
      "post_switch_final_hold_mean": 0.0,
      "post_switch_final_hold_max": 0.0,
      "focus_peak_target_score_mean": 7.435634414128829e-07,
      "focus_peak_target_score_max": 7.959300750739359e-07,
      "focus_peak_effective_target_score_mean": 7.435634414128829e-07,
      "focus_peak_effective_target_score_max": 7.959300750739359e-07,
      "focus_final_hold_mean": 0.0,
      "focus_final_hold_max": 0.0,
      "focus_overall_hold_mean": 0.0,
      "focus_overall_hold_max": 0.0,
      "focus_near_target_fraction_mean": 0.0,
      "focus_near_target_fraction_max": 0.0,
      "focus_near_fast_fraction_mean": 0.0,
      "focus_near_fast_fraction_max": 0.0,
      "focus_mean_angular_speed_near_mean": 0.0,
      "focus_mean_angular_speed_near_max": 0.0,
      "focus_max_in_target_streak_mean": 0.0,
      "focus_max_in_target_streak_max": 0.0,
      "terminations": {
        "max_steps": 3
      }
    },
    "capture_vertical": {
      "steps_mean": 1000.0,
      "steps_max": 1000.0,
      "total_reward_mean": -28.892238657277613,
      "total_reward_max": 80.63935031564569,
      "peak_target_score_mean": 0.996299814408714,
      "peak_target_score_max": 0.9988478465824634,
      "peak_effective_target_score_mean": 0.897083082473982,
      "peak_effective_target_score_max": 0.9863162640942134,
      "final_hold_mean": 0.0,
      "final_hold_max": 0.0,
      "overall_hold_mean": 0.052333333333333336,
      "overall_hold_max": 0.081,
      "max_in_target_streak_mean": 52.333333333333336,
      "max_in_target_streak_max": 81.0,
      "near_target_fraction_mean": 0.07733333333333332,
      "near_target_fraction_max": 0.102,
      "near_fast_fraction_mean": 0.049999999999999996,
      "near_fast_fraction_max": 0.073,
      "mean_angular_speed_near_mean": 1.8863791318346455,
      "mean_angular_speed_near_max": 2.615824660510342,
      "max_abs_cart_x_mean": 0.4693162781182682,
      "max_abs_cart_x_max": 0.5507004490454107,
      "mean_abs_action_mean": 0.03965166973349308,
      "mean_abs_action_max": 0.053424545026413396,
      "saturated_action_fraction_mean": 0.0033333333333333335,
      "saturated_action_fraction_max": 0.005,
      "pre_switch_final_hold_mean": 0.0,
      "pre_switch_final_hold_max": 0.0,
      "post_switch_final_hold_mean": 0.0,
      "post_switch_final_hold_max": 0.0,
      "focus_peak_target_score_mean": 0.996299814408714,
      "focus_peak_target_score_max": 0.9988478465824634,
      "focus_peak_effective_target_score_mean": 0.897083082473982,
      "focus_peak_effective_target_score_max": 0.9863162640942134,
      "focus_final_hold_mean": 0.0,
      "focus_final_hold_max": 0.0,
      "focus_overall_hold_mean": 0.052333333333333336,
      "focus_overall_hold_max": 0.081,
      "focus_near_target_fraction_mean": 0.07733333333333332,
      "focus_near_target_fraction_max": 0.102,
      "focus_near_fast_fraction_mean": 0.049999999999999996,
      "focus_near_fast_fraction_max": 0.073,
      "focus_mean_angular_speed_near_mean": 1.8863791318346455,
      "focus_mean_angular_speed_near_max": 2.615824660510342,
      "focus_max_in_target_streak_mean": 52.333333333333336,
      "focus_max_in_target_streak_max": 81.0,
      "terminations": {
        "max_steps": 3
      }
    },
    "fold_to_up": {
      "steps_mean": 1000.0,
      "steps_max": 1000.0,
      "total_reward_mean": -899.1367401585961,
      "total_reward_max": -780.0532366375112,
      "peak_target_score_mean": 0.9993752012881342,
      "peak_target_score_max": 0.9999997990701209,
      "peak_effective_target_score_mean": 0.9993752012881342,
      "peak_effective_target_score_max": 0.9999997990701209,
      "final_hold_mean": 0.0,
      "final_hold_max": 0.0,
      "overall_hold_mean": 0.09200000000000001,
      "overall_hold_max": 0.13,
      "max_in_target_streak_mean": 92.0,
      "max_in_target_streak_max": 130.0,
      "near_target_fraction_mean": 0.09566666666666668,
      "near_target_fraction_max": 0.134,
      "near_fast_fraction_mean": 0.008,
      "near_fast_fraction_max": 0.015,
      "mean_angular_speed_near_mean": 0.9464573410890486,
      "mean_angular_speed_near_max": 1.1683032730308647,
      "max_abs_cart_x_mean": 0.3225748848112704,
      "max_abs_cart_x_max": 0.3752175687612892,
      "mean_abs_action_mean": 0.015222272387337093,
      "mean_abs_action_max": 0.01598704941435426,
      "saturated_action_fraction_mean": 0.0,
      "saturated_action_fraction_max": 0.0,
      "pre_switch_final_hold_mean": 0.6153846153846154,
      "pre_switch_final_hold_max": 1.0,
      "post_switch_final_hold_mean": 0.0,
      "post_switch_final_hold_max": 0.0,
      "focus_peak_target_score_mean": 0.009740110727041488,
      "focus_peak_target_score_max": 0.018862458456211012,
      "focus_peak_effective_target_score_mean": 0.009740110727041488,
      "focus_peak_effective_target_score_max": 0.018862458456211012,
      "focus_final_hold_mean": 0.0,
      "focus_final_hold_max": 0.0,
      "focus_overall_hold_mean": 0.0,
      "focus_overall_hold_max": 0.0,
      "focus_near_target_fraction_mean": 0.0,
      "focus_near_target_fraction_max": 0.0,
      "focus_near_fast_fraction_mean": 0.0,
      "focus_near_fast_fraction_max": 0.0,
      "focus_mean_angular_speed_near_mean": 0.0,
      "focus_mean_angular_speed_near_max": 0.0,
      "focus_max_in_target_streak_mean": 0.0,
      "focus_max_in_target_streak_max": 0.0,
      "terminations": {
        "max_steps": 3
      }
    },
    "up_to_fold": {
      "steps_mean": 1000.0,
      "steps_max": 1000.0,
      "total_reward_mean": -1275.6122201891737,
      "total_reward_max": -1158.064794084727,
      "peak_target_score_mean": 0.998550262820407,
      "peak_target_score_max": 0.9999362342866681,
      "peak_effective_target_score_mean": 0.998550262820407,
      "peak_effective_target_score_max": 0.9999362342866681,
      "final_hold_mean": 0.0,
      "final_hold_max": 0.0,
      "overall_hold_mean": 0.10199999999999998,
      "overall_hold_max": 0.141,
      "max_in_target_streak_mean": 102.0,
      "max_in_target_streak_max": 141.0,
      "near_target_fraction_mean": 0.10299999999999998,
      "near_target_fraction_max": 0.144,
      "near_fast_fraction_mean": 0.0,
      "near_fast_fraction_max": 0.0,
      "mean_angular_speed_near_mean": 0.27019818880979773,
      "mean_angular_speed_near_max": 0.3672499804329721,
      "max_abs_cart_x_mean": 0.4859635156096753,
      "max_abs_cart_x_max": 0.6257887919568976,
      "mean_abs_action_mean": 0.04496304095518038,
      "mean_abs_action_max": 0.06744237047040952,
      "saturated_action_fraction_mean": 0.0,
      "saturated_action_fraction_max": 0.0,
      "pre_switch_final_hold_mean": 0.9642857142857143,
      "pre_switch_final_hold_max": 1.0,
      "post_switch_final_hold_mean": 0.0,
      "post_switch_final_hold_max": 0.0,
      "focus_peak_target_score_mean": 0.3606378676714966,
      "focus_peak_target_score_max": 0.6318324017135175,
      "focus_peak_effective_target_score_mean": 0.3606378676714966,
      "focus_peak_effective_target_score_max": 0.6318324017135175,
      "focus_final_hold_mean": 0.0,
      "focus_final_hold_max": 0.0,
      "focus_overall_hold_mean": 0.0,
      "focus_overall_hold_max": 0.0,
      "focus_near_target_fraction_mean": 0.0,
      "focus_near_target_fraction_max": 0.0,
      "focus_near_fast_fraction_mean": 0.0,
      "focus_near_fast_fraction_max": 0.0,
      "focus_mean_angular_speed_near_mean": 0.0,
      "focus_mean_angular_speed_near_max": 0.0,
      "focus_max_in_target_streak_mean": 0.0,
      "focus_max_in_target_streak_max": 0.0,
      "terminations": {
        "max_steps": 3
      }
    }
  },
  "episodes": [
    {
      "mode": "down_to_up",
      "episode_index": 0,
      "steps": 1000,
      "total_reward": -5.8699046638878105,
      "mean_reward": -0.005869904663887813,
      "termination_reason": "max_steps",
      "peak_target_score": 7.959300750739359e-07,
      "peak_effective_target_score": 7.959300750739359e-07,
      "mean_effective_target_score": 7.08682189602075e-07,
      "final_hold": 0.0,
      "overall_hold": 0.0,
      "max_in_target_streak": 0,
      "first_near_step": null,
      "near_target_fraction": 0.0,
      "near_fast_fraction": 0.0,
      "mean_angular_speed_near": 0.0,
      "max_angular_speed_near": 0.0,
      "max_abs_cart_x": 0.12812126144008015,
      "mean_abs_action": 0.00613209316819848,
      "saturated_action_fraction": 0.0,
      "pre_switch_peak_target_score": 7.959300750739359e-07,
      "pre_switch_peak_effective_target_score": 7.959300750739359e-07,
      "pre_switch_final_hold": 0.0,
      "pre_switch_overall_hold": 0.0,
      "pre_switch_near_target_fraction": 0.0,
      "pre_switch_near_fast_fraction": 0.0,
      "pre_switch_mean_angular_speed_near": 0.0,
      "pre_switch_max_in_target_streak": 0,
      "post_switch_peak_target_score": 0.0,
      "post_switch_peak_effective_target_score": 0.0,
      "post_switch_final_hold": 0.0,
      "post_switch_overall_hold": 0.0,
      "post_switch_near_target_fraction": 0.0,
      "post_switch_near_fast_fraction": 0.0,
      "post_switch_mean_angular_speed_near": 0.0,
      "post_switch_max_in_target_streak": 0,
      "focus_peak_target_score": 7.959300750739359e-07,
      "focus_peak_effective_target_score": 7.959300750739359e-07,
      "focus_final_hold": 0.0,
      "focus_overall_hold": 0.0,
      "focus_near_target_fraction": 0.0,
      "focus_near_fast_fraction": 0.0,
      "focus_mean_angular_speed_near": 0.0,
      "focus_max_in_target_streak": 0
    },
    {
      "mode": "down_to_up",
      "episode_index": 1,
      "steps": 1000,
      "total_reward": -6.257828791586469,
      "mean_reward": -0.006257828791586471,
      "termination_reason": "max_steps",
      "peak_target_score": 7.236743701888333e-07,
      "peak_effective_target_score": 7.236743701888333e-07,
      "mean_effective_target_score": 6.899239386651023e-07,
      "final_hold": 0.0,
      "overall_hold": 0.0,
      "max_in_target_streak": 0,
      "first_near_step": null,
      "near_target_fraction": 0.0,
      "near_fast_fraction": 0.0,
      "mean_angular_speed_near": 0.0,
      "max_angular_speed_near": 0.0,
      "max_abs_cart_x": 0.13813924428940755,
      "mean_abs_action": 0.004676738320515142,
      "saturated_action_fraction": 0.0,
      "pre_switch_peak_target_score": 7.236743701888333e-07,
      "pre_switch_peak_effective_target_score": 7.236743701888333e-07,
      "pre_switch_final_hold": 0.0,
      "pre_switch_overall_hold": 0.0,
      "pre_switch_near_target_fraction": 0.0,
      "pre_switch_near_fast_fraction": 0.0,
      "pre_switch_mean_angular_speed_near": 0.0,
      "pre_switch_max_in_target_streak": 0,
      "post_switch_peak_target_score": 0.0,
      "post_switch_peak_effective_target_score": 0.0,
      "post_switch_final_hold": 0.0,
      "post_switch_overall_hold": 0.0,
      "post_switch_near_target_fraction": 0.0,
      "post_switch_near_fast_fraction": 0.0,
      "post_switch_mean_angular_speed_near": 0.0,
      "post_switch_max_in_target_streak": 0,
      "focus_peak_target_score": 7.236743701888333e-07,
      "focus_peak_effective_target_score": 7.236743701888333e-07,
      "focus_final_hold": 0.0,
      "focus_overall_hold": 0.0,
      "focus_near_target_fraction": 0.0,
      "focus_near_fast_fraction": 0.0,
      "focus_mean_angular_speed_near": 0.0,
      "focus_max_in_target_streak": 0
    },
    {
      "mode": "down_to_up",
      "episode_index": 2,
      "steps": 1000,
      "total_reward": -5.905316020045879,
      "mean_reward": -0.005905316020045882,
      "termination_reason": "max_steps",
      "peak_target_score": 7.110858789758797e-07,
      "peak_effective_target_score": 7.110858789758797e-07,
      "mean_effective_target_score": 6.843648678110803e-07,
      "final_hold": 0.0,
      "overall_hold": 0.0,
      "max_in_target_streak": 0,
      "first_near_step": null,
      "near_target_fraction": 0.0,
      "near_fast_fraction": 0.0,
      "mean_angular_speed_near": 0.0,
      "max_angular_speed_near": 0.0,
      "max_abs_cart_x": 0.13594927465984963,
      "mean_abs_action": 0.004091981638688594,
      "saturated_action_fraction": 0.0,
      "pre_switch_peak_target_score": 7.110858789758797e-07,
      "pre_switch_peak_effective_target_score": 7.110858789758797e-07,
      "pre_switch_final_hold": 0.0,
      "pre_switch_overall_hold": 0.0,
      "pre_switch_near_target_fraction": 0.0,
      "pre_switch_near_fast_fraction": 0.0,
      "pre_switch_mean_angular_speed_near": 0.0,
      "pre_switch_max_in_target_streak": 0,
      "post_switch_peak_target_score": 0.0,
      "post_switch_peak_effective_target_score": 0.0,
      "post_switch_final_hold": 0.0,
      "post_switch_overall_hold": 0.0,
      "post_switch_near_target_fraction": 0.0,
      "post_switch_near_fast_fraction": 0.0,
      "post_switch_mean_angular_speed_near": 0.0,
      "post_switch_max_in_target_streak": 0,
      "focus_peak_target_score": 7.110858789758797e-07,
      "focus_peak_effective_target_score": 7.110858789758797e-07,
      "focus_final_hold": 0.0,
      "focus_overall_hold": 0.0,
      "focus_near_target_fraction": 0.0,
      "focus_near_fast_fraction": 0.0,
      "focus_mean_angular_speed_near": 0.0,
      "focus_max_in_target_streak": 0
    },
    {
      "mode": "capture_vertical",
      "episode_index": 0,
      "steps": 1000,
      "total_reward": -81.93609125319371,
      "mean_reward": -0.08193609125319369,
      "termination_reason": "max_steps",
      "peak_target_score": 0.9987362715633624,
      "peak_effective_target_score": 0.9570956787378302,
      "mean_effective_target_score": 0.08401154850271912,
      "final_hold": 0.0,
      "overall_hold": 0.044,
      "max_in_target_streak": 44,
      "first_near_step": 0,
      "near_target_fraction": 0.073,
      "near_fast_fraction": 0.073,
      "mean_angular_speed_near": 1.8844006666835411,
      "max_angular_speed_near": 3.91917590391058,
      "max_abs_cart_x": 0.5507004490454107,
      "mean_abs_action": 0.053424545026413396,
      "saturated_action_fraction": 0.005,
      "pre_switch_peak_target_score": 0.9987362715633624,
      "pre_switch_peak_effective_target_score": 0.9570956787378302,
      "pre_switch_final_hold": 0.0,
      "pre_switch_overall_hold": 0.044,
      "pre_switch_near_target_fraction": 0.073,
      "pre_switch_near_fast_fraction": 0.073,
      "pre_switch_mean_angular_speed_near": 1.8844006666835411,
      "pre_switch_max_in_target_streak": 44,
      "post_switch_peak_target_score": 0.0,
      "post_switch_peak_effective_target_score": 0.0,
      "post_switch_final_hold": 0.0,
      "post_switch_overall_hold": 0.0,
      "post_switch_near_target_fraction": 0.0,
      "post_switch_near_fast_fraction": 0.0,
      "post_switch_mean_angular_speed_near": 0.0,
      "post_switch_max_in_target_streak": 0,
      "focus_peak_target_score": 0.9987362715633624,
      "focus_peak_effective_target_score": 0.9570956787378302,
      "focus_final_hold": 0.0,
      "focus_overall_hold": 0.044,
      "focus_near_target_fraction": 0.073,
      "focus_near_fast_fraction": 0.073,
      "focus_mean_angular_speed_near": 1.8844006666835411,
      "focus_max_in_target_streak": 44
    },
    {
      "mode": "capture_vertical",
      "episode_index": 1,
      "steps": 1000,
      "total_reward": -85.37997503428483,
      "mean_reward": -0.08537997503428477,
      "termination_reason": "max_steps",
      "peak_target_score": 0.9988478465824634,
      "peak_effective_target_score": 0.7478373045899024,
      "mean_effective_target_score": 0.056220516488351635,
      "final_hold": 0.0,
      "overall_hold": 0.032,
      "max_in_target_streak": 32,
      "first_near_step": 0,
      "near_target_fraction": 0.057,
      "near_fast_fraction": 0.057,
      "mean_angular_speed_near": 2.615824660510342,
      "max_angular_speed_near": 4.7440883401493235,
      "max_abs_cart_x": 0.333692434899337,
      "mean_abs_action": 0.020707301141999777,
      "saturated_action_fraction": 0.002,
      "pre_switch_peak_target_score": 0.9988478465824634,
      "pre_switch_peak_effective_target_score": 0.7478373045899024,
      "pre_switch_final_hold": 0.0,
      "pre_switch_overall_hold": 0.032,
      "pre_switch_near_target_fraction": 0.057,
      "pre_switch_near_fast_fraction": 0.057,
      "pre_switch_mean_angular_speed_near": 2.615824660510342,
      "pre_switch_max_in_target_streak": 32,
      "post_switch_peak_target_score": 0.0,
      "post_switch_peak_effective_target_score": 0.0,
      "post_switch_final_hold": 0.0,
      "post_switch_overall_hold": 0.0,
      "post_switch_near_target_fraction": 0.0,
      "post_switch_near_fast_fraction": 0.0,
      "post_switch_mean_angular_speed_near": 0.0,
      "post_switch_max_in_target_streak": 0,
      "focus_peak_target_score": 0.9988478465824634,
      "focus_peak_effective_target_score": 0.7478373045899024,
      "focus_final_hold": 0.0,
      "focus_overall_hold": 0.032,
      "focus_near_target_fraction": 0.057,
      "focus_near_fast_fraction": 0.057,
      "focus_mean_angular_speed_near": 2.615824660510342,
      "focus_max_in_target_streak": 32
    },
    {
      "mode": "capture_vertical",
      "episode_index": 2,
      "steps": 1000,
      "total_reward": 80.63935031564569,
      "mean_reward": 0.0806393503156458,
      "termination_reason": "max_steps",
      "peak_target_score": 0.9913153250803162,
      "peak_effective_target_score": 0.9863162640942134,
      "mean_effective_target_score": 0.12107383530880854,
      "final_hold": 0.0,
      "overall_hold": 0.081,
      "max_in_target_streak": 81,
      "first_near_step": 0,
      "near_target_fraction": 0.102,
      "near_fast_fraction": 0.02,
      "mean_angular_speed_near": 1.1589120683100536,
      "max_angular_speed_near": 2.861792748692018,
      "max_abs_cart_x": 0.5235559504100568,
      "mean_abs_action": 0.04482316303206608,
      "saturated_action_fraction": 0.003,
      "pre_switch_peak_target_score": 0.9913153250803162,
      "pre_switch_peak_effective_target_score": 0.9863162640942134,
      "pre_switch_final_hold": 0.0,
      "pre_switch_overall_hold": 0.081,
      "pre_switch_near_target_fraction": 0.102,
      "pre_switch_near_fast_fraction": 0.02,
      "pre_switch_mean_angular_speed_near": 1.1589120683100536,
      "pre_switch_max_in_target_streak": 81,
      "post_switch_peak_target_score": 0.0,
      "post_switch_peak_effective_target_score": 0.0,
      "post_switch_final_hold": 0.0,
      "post_switch_overall_hold": 0.0,
      "post_switch_near_target_fraction": 0.0,
      "post_switch_near_fast_fraction": 0.0,
      "post_switch_mean_angular_speed_near": 0.0,
      "post_switch_max_in_target_streak": 0,
      "focus_peak_target_score": 0.9913153250803162,
      "focus_peak_effective_target_score": 0.9863162640942134,
      "focus_final_hold": 0.0,
      "focus_overall_hold": 0.081,
      "focus_near_target_fraction": 0.102,
      "focus_near_fast_fraction": 0.02,
      "focus_mean_angular_speed_near": 1.1589120683100536,
      "focus_max_in_target_streak": 81
    },
    {
      "mode": "fold_to_up",
      "episode_index": 0,
      "steps": 1000,
      "total_reward": -780.0532366375112,
      "mean_reward": -0.7800532366375117,
      "termination_reason": "max_steps",
      "peak_target_score": 0.9999997317281478,
      "peak_effective_target_score": 0.9999997317281478,
      "mean_effective_target_score": 0.12893171589976826,
      "final_hold": 0.0,
      "overall_hold": 0.13,
      "max_in_target_streak": 130,
      "first_near_step": 0,
      "near_target_fraction": 0.134,
      "near_fast_fraction": 0.009,
      "mean_angular_speed_near": 0.8653642399510195,
      "max_angular_speed_near": 1.5987930636985286,
      "max_abs_cart_x": 0.3752175687612892,
      "mean_abs_action": 0.015142759354843292,
      "saturated_action_fraction": 0.0,
      "pre_switch_peak_target_score": 0.9999997317281478,
      "pre_switch_peak_effective_target_score": 0.9999997317281478,
      "pre_switch_final_hold": 0.8461538461538461,
      "pre_switch_overall_hold": 0.9701492537313433,
      "pre_switch_near_target_fraction": 1.0,
      "pre_switch_near_fast_fraction": 0.06716417910447761,
      "pre_switch_mean_angular_speed_near": 0.8653642399510195,
      "pre_switch_max_in_target_streak": 130,
      "post_switch_peak_target_score": 0.007975861748680991,
      "post_switch_peak_effective_target_score": 0.007975861748680991,
      "post_switch_final_hold": 0.0,
      "post_switch_overall_hold": 0.0,
      "post_switch_near_target_fraction": 0.0,
      "post_switch_near_fast_fraction": 0.0,
      "post_switch_mean_angular_speed_near": 0.0,
      "post_switch_max_in_target_streak": 0,
      "focus_peak_target_score": 0.007975861748680991,
      "focus_peak_effective_target_score": 0.007975861748680991,
      "focus_final_hold": 0.0,
      "focus_overall_hold": 0.0,
      "focus_near_target_fraction": 0.0,
      "focus_near_fast_fraction": 0.0,
      "focus_mean_angular_speed_near": 0.0,
      "focus_max_in_target_streak": 0
    },
    {
      "mode": "fold_to_up",
      "episode_index": 1,
      "steps": 1000,
      "total_reward": -1022.2052311757501,
      "mean_reward": -1.0222052311757488,
      "termination_reason": "max_steps",
      "peak_target_score": 0.9999997990701209,
      "peak_effective_target_score": 0.9999997990701209,
      "mean_effective_target_score": 0.06596735439665498,
      "final_hold": 0.0,
      "overall_hold": 0.066,
      "max_in_target_streak": 66,
      "first_near_step": 0,
      "near_target_fraction": 0.066,
      "near_fast_fraction": 0.0,
      "mean_angular_speed_near": 0.8057045102852617,
      "max_angular_speed_near": 1.1718157103809987,
      "max_abs_cart_x": 0.2998365914025308,
      "mean_abs_action": 0.014537008392813732,
      "saturated_action_fraction": 0.0,
      "pre_switch_peak_target_score": 0.9999997990701209,
      "pre_switch_peak_effective_target_score": 0.9999997990701209,
      "pre_switch_final_hold": 1.0,
      "pre_switch_overall_hold": 1.0,
      "pre_switch_near_target_fraction": 1.0,
      "pre_switch_near_fast_fraction": 0.0,
      "pre_switch_mean_angular_speed_near": 0.8057045102852617,
      "pre_switch_max_in_target_streak": 66,
      "post_switch_peak_target_score": 0.018862458456211012,
      "post_switch_peak_effective_target_score": 0.018862458456211012,
      "post_switch_final_hold": 0.0,
      "post_switch_overall_hold": 0.0,
      "post_switch_near_target_fraction": 0.0,
      "post_switch_near_fast_fraction": 0.0,
      "post_switch_mean_angular_speed_near": 0.0,
      "post_switch_max_in_target_streak": 0,
      "focus_peak_target_score": 0.018862458456211012,
      "focus_peak_effective_target_score": 0.018862458456211012,
      "focus_final_hold": 0.0,
      "focus_overall_hold": 0.0,
      "focus_near_target_fraction": 0.0,
      "focus_near_fast_fraction": 0.0,
      "focus_mean_angular_speed_near": 0.0,
      "focus_max_in_target_streak": 0
    },
    {
      "mode": "fold_to_up",
      "episode_index": 2,
      "steps": 1000,
      "total_reward": -895.1517526625271,
      "mean_reward": -0.8951517526625284,
      "termination_reason": "max_steps",
      "peak_target_score": 0.9981260730661335,
      "peak_effective_target_score": 0.9981260730661335,
      "mean_effective_target_score": 0.09879996766434508,
      "final_hold": 0.0,
      "overall_hold": 0.08,
      "max_in_target_streak": 80,
      "first_near_step": 0,
      "near_target_fraction": 0.087,
      "near_fast_fraction": 0.015,
      "mean_angular_speed_near": 1.1683032730308647,
      "max_angular_speed_near": 1.653961987758324,
      "max_abs_cart_x": 0.2926704942699911,
      "mean_abs_action": 0.01598704941435426,
      "saturated_action_fraction": 0.0,
      "pre_switch_peak_target_score": 0.9981260730661335,
      "pre_switch_peak_effective_target_score": 0.9981260730661335,
      "pre_switch_final_hold": 0.0,
      "pre_switch_overall_hold": 0.6896551724137931,
      "pre_switch_near_target_fraction": 0.75,
      "pre_switch_near_fast_fraction": 0.12931034482758622,
      "pre_switch_mean_angular_speed_near": 1.1683032730308647,
      "pre_switch_max_in_target_streak": 80,
      "post_switch_peak_target_score": 0.0023820119762324597,
      "post_switch_peak_effective_target_score": 0.0023820119762324597,
      "post_switch_final_hold": 0.0,
      "post_switch_overall_hold": 0.0,
      "post_switch_near_target_fraction": 0.0,
      "post_switch_near_fast_fraction": 0.0,
      "post_switch_mean_angular_speed_near": 0.0,
      "post_switch_max_in_target_streak": 0,
      "focus_peak_target_score": 0.0023820119762324597,
      "focus_peak_effective_target_score": 0.0023820119762324597,
      "focus_final_hold": 0.0,
      "focus_overall_hold": 0.0,
      "focus_near_target_fraction": 0.0,
      "focus_near_fast_fraction": 0.0,
      "focus_mean_angular_speed_near": 0.0,
      "focus_max_in_target_streak": 0
    },
    {
      "mode": "up_to_fold",
      "episode_index": 0,
      "steps": 1000,
      "total_reward": -1274.076539362695,
      "mean_reward": -1.274076539362694,
      "termination_reason": "max_steps",
      "peak_target_score": 0.9999362342866681,
      "peak_effective_target_score": 0.9999362342866681,
      "mean_effective_target_score": 0.14570611937907235,
      "final_hold": 0.0,
      "overall_hold": 0.091,
      "max_in_target_streak": 91,
      "first_near_step": 0,
      "near_target_fraction": 0.091,
      "near_fast_fraction": 0.0,
      "mean_angular_speed_near": 0.2289798395685184,
      "max_angular_speed_near": 0.4286598825118078,
      "max_abs_cart_x": 0.6257887919568976,
      "mean_abs_action": 0.024085730996797793,
      "saturated_action_fraction": 0.0,
      "pre_switch_peak_target_score": 0.9999362342866681,
      "pre_switch_peak_effective_target_score": 0.9999362342866681,
      "pre_switch_final_hold": 1.0,
      "pre_switch_overall_hold": 1.0,
      "pre_switch_near_target_fraction": 1.0,
      "pre_switch_near_fast_fraction": 0.0,
      "pre_switch_mean_angular_speed_near": 0.2289798395685184,
      "pre_switch_max_in_target_streak": 91,
      "post_switch_peak_target_score": 0.6318324017135175,
      "post_switch_peak_effective_target_score": 0.6318324017135175,
      "post_switch_final_hold": 0.0,
      "post_switch_overall_hold": 0.0,
      "post_switch_near_target_fraction": 0.0,
      "post_switch_near_fast_fraction": 0.0,
      "post_switch_mean_angular_speed_near": 0.0,
      "post_switch_max_in_target_streak": 0,
      "focus_peak_target_score": 0.6318324017135175,
      "focus_peak_effective_target_score": 0.6318324017135175,
      "focus_final_hold": 0.0,
      "focus_overall_hold": 0.0,
      "focus_near_target_fraction": 0.0,
      "focus_near_fast_fraction": 0.0,
      "focus_mean_angular_speed_near": 0.0,
      "focus_max_in_target_streak": 0
    },
    {
      "mode": "up_to_fold",
      "episode_index": 1,
      "steps": 1000,
      "total_reward": -1394.6953271200996,
      "mean_reward": -1.3946953271201,
      "termination_reason": "max_steps",
      "peak_target_score": 0.9992139989235072,
      "peak_effective_target_score": 0.9992139989235072,
      "mean_effective_target_score": 0.09831587122433709,
      "final_hold": 0.0,
      "overall_hold": 0.074,
      "max_in_target_streak": 74,
      "first_near_step": 0,
      "near_target_fraction": 0.074,
      "near_fast_fraction": 0.0,
      "mean_angular_speed_near": 0.21436474642790274,
      "max_angular_speed_near": 0.2608438578085019,
      "max_abs_cart_x": 0.3956554295619287,
      "mean_abs_action": 0.06744237047040952,
      "saturated_action_fraction": 0.0,
      "pre_switch_peak_target_score": 0.9992139989235072,
      "pre_switch_peak_effective_target_score": 0.9992139989235072,
      "pre_switch_final_hold": 1.0,
      "pre_switch_overall_hold": 1.0,
      "pre_switch_near_target_fraction": 1.0,
      "pre_switch_near_fast_fraction": 0.0,
      "pre_switch_mean_angular_speed_near": 0.21436474642790274,
      "pre_switch_max_in_target_streak": 74,
      "post_switch_peak_target_score": 0.14936804188518074,
      "post_switch_peak_effective_target_score": 0.14936804188518074,
      "post_switch_final_hold": 0.0,
      "post_switch_overall_hold": 0.0,
      "post_switch_near_target_fraction": 0.0,
      "post_switch_near_fast_fraction": 0.0,
      "post_switch_mean_angular_speed_near": 0.0,
      "post_switch_max_in_target_streak": 0,
      "focus_peak_target_score": 0.14936804188518074,
      "focus_peak_effective_target_score": 0.14936804188518074,
      "focus_final_hold": 0.0,
      "focus_overall_hold": 0.0,
      "focus_near_target_fraction": 0.0,
      "focus_near_fast_fraction": 0.0,
      "focus_mean_angular_speed_near": 0.0,
      "focus_max_in_target_streak": 0
    },
    {
      "mode": "up_to_fold",
      "episode_index": 2,
      "steps": 1000,
      "total_reward": -1158.064794084727,
      "mean_reward": -1.1580647940847264,
      "termination_reason": "max_steps",
      "peak_target_score": 0.9965005552510456,
      "peak_effective_target_score": 0.9965005552510456,
      "mean_effective_target_score": 0.1702174677299883,
      "final_hold": 0.0,
      "overall_hold": 0.141,
      "max_in_target_streak": 141,
      "first_near_step": 0,
      "near_target_fraction": 0.144,
      "near_fast_fraction": 0.0,
      "mean_angular_speed_near": 0.3672499804329721,
      "max_angular_speed_near": 0.7657605395438166,
      "max_abs_cart_x": 0.43644632531019983,
      "mean_abs_action": 0.04336102139833383,
      "saturated_action_fraction": 0.0,
      "pre_switch_peak_target_score": 0.9965005552510456,
      "pre_switch_peak_effective_target_score": 0.9965005552510456,
      "pre_switch_final_hold": 0.8928571428571429,
      "pre_switch_overall_hold": 0.9791666666666666,
      "pre_switch_near_target_fraction": 1.0,
      "pre_switch_near_fast_fraction": 0.0,
      "pre_switch_mean_angular_speed_near": 0.3672499804329721,
      "pre_switch_max_in_target_streak": 141,
      "post_switch_peak_target_score": 0.30071315941579163,
      "post_switch_peak_effective_target_score": 0.30071315941579163,
      "post_switch_final_hold": 0.0,
      "post_switch_overall_hold": 0.0,
      "post_switch_near_target_fraction": 0.0,
      "post_switch_near_fast_fraction": 0.0,
      "post_switch_mean_angular_speed_near": 0.0,
      "post_switch_max_in_target_streak": 0,
      "focus_peak_target_score": 0.30071315941579163,
      "focus_peak_effective_target_score": 0.30071315941579163,
      "focus_final_hold": 0.0,
      "focus_overall_hold": 0.0,
      "focus_near_target_fraction": 0.0,
      "focus_near_fast_fraction": 0.0,
      "focus_mean_angular_speed_near": 0.0,
      "focus_max_in_target_streak": 0
    }
  ]
}